setup.cfg
setup.py
BezdarSQL.egg-info/PKG-INFO
BezdarSQL.egg-info/SOURCES.txt
BezdarSQL.egg-info/dependency_links.txt
BezdarSQL.egg-info/not-zip-safe
BezdarSQL.egg-info/top_level.txt
bezdarsql/__init__.py
bezdarsql/base.py
bezdarsql/config.py