Metadata-Version: 2.4
Name: BezdarSQL
Version: 1.0
Summary: My little SQL ORM for the ones who called bezdars
Author-email: boliklevik@gmail.com
Dynamic: author-email
Dynamic: summary
